Workbook

Sheet Raw Data
A1: Order ID | B1: Order Date | C1: Category | D1: Product | E1: Unit Price | F1: Discount % | G1: Units Sold | H1: Unit Cost | I1: Revenue | J1: Cost | K1: Profit
A2: 1151 | B2: 2026-01-01 | C2: Electronics | D2: Wireless Earbuds | E2: 3040 | F2: 0.3 | G2: 28 | H2: 2432 | I2: 59584 | J2: 68096 | K2: -8512
A3: 1124 | B3: 2026-01-03 | C3: Home Goods | D3: Table Fan | E3: 790 | F3: 0.2 | G3: 17 | H3: 489.8 | I3: 10744 | J3: 8326.6 | K3: 2417.4
A4: 1097 | B4: 2026-01-03 | C4: Home Goods | D4: Table Fan | E4: 1190 | F4: 0.1 | G4: 12 | H4: 737.8 | I4: 12852 | J4: 8853.6 | K4: 3998.4
A5: 1267 | B5: 2026-01-03 | C5: Home Goods | D5: LED Desk Lamp | E5: 1890 | F5: 0.1 | G5: 12 | H5: 1171.8 | I5: 20412 | J5: 14061.6 | K5: 6350.4
A6: 1062 | B6: 2026-01-04 | C6: Home Goods | D6: Table Fan | E6: 1420 | F6: 0.1 | G6: 11 | H6: 880.4 | I6: 14058 | J6: 9684.4 | K6: 4373.6
A7: 1014 | B7: 2026-01-05 | C7: Apparel | D7: Running Shoes | E7: 1670 | F7: 0.2 | G7: 18 | H7: 835 | I7: 24048 | J7: 15030 | K7: 9018
A8: 1195 | B8: 2026-01-05 | C8: Home Goods | D8: Non-stick Cookware Set | E8: 1090 | F8: 0 | G8: 11 | H8: 675.8 | I8: 11990 | J8: 7433.8 | K8: 4556.2
A9: 1297 | B9: 2026-01-06 | C9: Apparel | D9: Formal Shirt | E9: 900 | F9: 0.1 | G9: 17 | H9: 450 | I9: 13770 | J9: 7650 | K9: 6120
A10: 1233 | B10: 2026-01-07 | C10: Home Goods | D10: Table Fan | E10: 2520 | F10: 0.1 | G10: 33 | H10: 1562.4 | I10: 74844 | J10: 51559.2 | K10: 23284.8
A11: 1249 | B11: 2026-01-08 | C11: Home Goods | D11: Non-stick Cookware Set | E11: 1340 | F11: 0 | G11: 8 | H11: 830.8 | I11: 10720 | J11: 6646.4 | K11: 4073.6
A12: 1178 | B12: 2026-01-08 | C12: Electronics | D12: Smartwatch | E12: 2920 | F12: 0.3 | G12: 47 | H12: 2336 | I12: 96068 | J12: 109792 | K12: -13724
A13: 1006 | B13: 2026-01-09 | C13: Electronics | D13: Wireless Earbuds | E13: 1410 | F13: 0.3 | G13: 42 | H13: 1128 | I13: 41454 | J13: 47376 | K13: -5922
... A321: 1137 | B321: 2026-06-29 | C321: Electronics | D321: Smartwatch | E321: 3690 | F321: 0.4 | G321: 47 | H321: 2952 | I321: 104058 | J321: 138744 | K321: -34686

Sheet Summary
A1: Pricing & Discount Impact Summary
A2: All figures calculated via SUMIFS/AVERAGEIFS from Raw Data — recalculates automatically if Raw Data changes.
A4: By Discount Band
A5: Discount % | B5: Total Revenue | C5: Total Cost | D5: Total Profit | E5: Profit Margin % | F5: Units Sold
A6: 0 | B6: =SUMIFS('Raw Data'!I2:I321,'Raw Data'!F2:F321,A6) -> 1751620 | C6: =SUMIFS('Raw Data'!J2:J321,'Raw Data'!F2:F321,A6) -> 1196295.8 | D6: =B6-C6 -> 555324.2 | E6: =IFERROR(D6/B6,0) -> 0.31703463 | F6: =SUMIFS('Raw Data'!G2:G321,'Raw Data'!F2:F321,A6) -> 941
A7: 0.1 | B7: =SUMIFS('Raw Data'!I2:I321,'Raw Data'!F2:F321,A7) -> 2318463 | C7: =SUMIFS('Raw Data'!J2:J321,'Raw Data'!F2:F321,A7) -> 1671253.2 | D7: =B7-C7 -> 647209.8 | E7: =IFERROR(D7/B7,0) -> 0.27915468 | F7: =SUMIFS('Raw Data'!G2:G321,'Raw Data'!F2:F321,A7) -> 1460
A8: 0.2 | B8: =SUMIFS('Raw Data'!I2:I321,'Raw Data'!F2:F321,A8) -> 2388832 | C8: =SUMIFS('Raw Data'!J2:J321,'Raw Data'!F2:F321,A8) -> 2059474.6 | D8: =B8-C8 -> 329357.4 | E8: =IFERROR(D8/B8,0) -> 0.13787382 | F8: =SUMIFS('Raw Data'!G2:G321,'Raw Data'!F2:F321,A8) -> 1504
A9: 0.3 | B9: =SUMIFS('Raw Data'!I2:I321,'Raw Data'!F2:F321,A9) -> 2890825 | C9: =SUMIFS('Raw Data'!J2:J321,'Raw Data'!F2:F321,A9) -> 2832520.4 | D9: =B9-C9 -> 58304.6 | E9: =IFERROR(D9/B9,0) -> 0.020168845 | F9: =SUMIFS('Raw Data'!G2:G321,'Raw Data'!F2:F321,A9) -> 1971
A10: 0.4 | B10: =SUMIFS('Raw Data'!I2:I321,'Raw Data'!F2:F321,A10) -> 2143188 | C10: =SUMIFS('Raw Data'!J2:J321,'Raw Data'!F2:F321,A10) -> 2390565 | D10: =B10-C10 -> -247377 | E10: =IFERROR(D10/B10,0) -> -0.11542478 | F10: =SUMIFS('Raw Data'!G2:G321,'Raw Data'!F2:F321,A10) -> 1934
A13: By Category
A14: Category | B14: Total Revenue | C14: Total Cost | D14: Total Profit | E14: Profit Margin % | F14: Units Sold
A15: Electronics | B15: =SUMIFS('Raw Data'!I2:I321,'Raw Data'!C2:C321,A15) -> 5426234 | C15: =SUMIFS('Raw Data'!J2:J321,'Raw Data'!C2:C321,A15) -> 5705224 | D15: =B15-C15 -> -278990 | E15: =IFERROR(D15/B15,0) -> -0.051415033 | F15: =SUMIFS('Raw Data'!G2:G321,'Raw Data'!C2:C321,A15) -> 2539
A16: Home Goods | B16: =SUMIFS('Raw Data'!I2:I321,'Raw Data'!C2:C321,A16) -> 3256437 | C16: =SUMIFS('Raw Data'!J2:J321,'Raw Data'!C2:C321,A16) -> 2598420 | D16: =B16-C16 -> 658017 | E16: =IFERROR(D16/B16,0) -> 0.20206655 | F16: =SUMIFS('Raw Data'!G2:G321,'Raw Data'!C2:C321,A16) -> 2550
A17: Apparel | B17: =SUMIFS('Raw Data'!I2:I321,'Raw Data'!C2:C321,A17) -> 2810257 | C17: =SUMIFS('Raw Data'!J2:J321,'Raw Data'!C2:C321,A17) -> 1846465 | D17: =B17-C17 -> 963792 | E17: =IFERROR(D17/B17,0) -> 0.34295511 | F17: =SUMIFS('Raw Data'!G2:G321,'Raw Data'!C2:C321,A17) -> 2721

Sheet Dashboard
A1: Retail Pricing & Discount Impact Dashboard
A2: Key question: are higher discounts actually increasing profit, or just increasing volume while eroding margin?
A4: Best-performing discount band | C4: Highest-discount band profit | E4: Total Profit (all orders)
A5: =INDEX(Summary!A6:A10,MATCH(MAX(Summary!D6:D10),Summary!D6:D10,0)) -> 0.1 | C5: =Summary!D10 -> -247377 | E5: =SUM(Summary!D6:D10) -> 1342819
A40: Note: Dataset is simulated for portfolio purposes. Category margins and discount-response curves are illustrative assumptions, not sourced from a real retailer.
